odoo/addons/product_product_template_navigation/README.rst
odoo/addons/product_product_template_navigation/__init__.py
odoo/addons/product_product_template_navigation/__manifest__.py
odoo/addons/product_product_template_navigation/i18n/es.po
odoo/addons/product_product_template_navigation/i18n/product_product_template_navigation.pot
odoo/addons/product_product_template_navigation/models/__init__.py
odoo/addons/product_product_template_navigation/models/product_product.py
odoo/addons/product_product_template_navigation/readme/CONTRIBUTORS.rst
odoo/addons/product_product_template_navigation/readme/DESCRIPTION.rst
odoo/addons/product_product_template_navigation/static/description/icon.png
odoo/addons/product_product_template_navigation/static/description/index.html
odoo/addons/product_product_template_navigation/static/img/template_navigation.gif
odoo/addons/product_product_template_navigation/views/product_product_views.xml
odoo13_addon_product_product_template_navigation-13.0.1.0.1.dist-info/METADATA
odoo13_addon_product_product_template_navigation-13.0.1.0.1.dist-info/WHEEL
odoo13_addon_product_product_template_navigation-13.0.1.0.1.dist-info/top_level.txt
odoo13_addon_product_product_template_navigation-13.0.1.0.1.dist-info/RECORD
